dismotif/__init__.py
dismotif/check_motifs.py
dismotif/check_motifs.sh
dismotif/find_disrupted_motifs.py
dismotif/var_to_hg19.py
dismotif-1.1.6.dist-info/LICENSE
dismotif-1.1.6.dist-info/METADATA
dismotif-1.1.6.dist-info/WHEEL
dismotif-1.1.6.dist-info/entry_points.txt
dismotif-1.1.6.dist-info/top_level.txt
dismotif-1.1.6.dist-info/RECORD
