Metadata-Version: 2.1
Name: dismotif
Version: 1.1.6
Summary: disrupted motifs
Home-page: https://gitlab.com/aaylward/dismotif
Author: Anthony Aylward, Joshua Chiou
Author-email: aaylward@salk.edu
License: UNKNOWN
Platform: UNKNOWN
Classifier: Programming Language :: Python :: 3
Classifier: License :: OSI Approved :: MIT License
Classifier: Operating System :: OS Independent
License-File: LICENSE
Requires-Dist: pybedtools
Requires-Dist: pyhg19
